dymachandran/__init__.py
dymachandran/main.py
dymachandran-0.0.2.dist-info/METADATA
dymachandran-0.0.2.dist-info/WHEEL
dymachandran-0.0.2.dist-info/entry_points.txt
dymachandran-0.0.2.dist-info/top_level.txt
dymachandran-0.0.2.dist-info/RECORD
