Metadata-Version: 2.1
Name: dymachandran
Version: 0.0.2
Summary: ramachandran plotter for molecular dynamics
Author: Nata Nobre
Author-email: natanobre0605@gmail.com
License: GNU GENERAL PUBLIC LICENSE
Keywords: ramachadran
Requires-Dist: numpy
Requires-Dist: pandas
Requires-Dist: plotly.express
Requires-Dist: argparse
Requires-Dist: Pillow
Requires-Dist: MDAnalysis
Requires-Dist: progressbar2
Requires-Dist: requests
